minterp/__init__.py
minterp/context.py
minterp/future_lens.py
minterp/learned_lens.py
minterp/logit_lens.py
minterp/metric.py
minterp/model.py
minterp/state.py
minterp/token_identity.py
minterp/token_identity_heatmap.py
minterp/vis.py
minterp-0.1.2.dist-info/METADATA
minterp-0.1.2.dist-info/WHEEL
minterp-0.1.2.dist-info/RECORD
