Metadata-Version: 2.1
Name: minterp
Version: 0.1.2
Summary: 
License: MIT
Author: fergus
Author-email: fergusfettes@gmail.com
Requires-Python: >=3.10,<4.0
Classifier: License :: OSI Approved :: MIT License
Classifier: Programming Language :: Python :: 3
Classifier: Programming Language :: Python :: 3.10
Classifier: Programming Language :: Python :: 3.11
Requires-Dist: nnsight (>=0.2.6,<0.3.0)
Requires-Dist: plotly (>=5.19.0,<6.0.0)
Requires-Dist: torchmetrics (>=1.3.1,<2.0.0)
